qingping_ble/__init__.py
qingping_ble/parser.py
qingping_ble/py.typed
qingping_ble-0.10.0.dist-info/LICENSE
qingping_ble-0.10.0.dist-info/METADATA
qingping_ble-0.10.0.dist-info/WHEEL
qingping_ble-0.10.0.dist-info/RECORD
