Metadata-Version: 2.1
Name: qingping-ble
Version: 0.10.0
Summary: Qingping BLE support
Home-page: https://github.com/bluetooth-devices/qingping-ble
License: MIT
Author: J. Nick Koston
Author-email: nick@koston.org
Requires-Python: >=3.9,<4.0
Classifier: Development Status :: 2 - Pre-Alpha
Classifier: Intended Audience :: Developers
Classifier: License :: OSI Approved :: MIT License
Classifier: Natural Language :: English
Classifier: Operating System :: OS Independent
Classifier: Programming Language :: Python :: 3
Classifier: Programming Language :: Python :: 3.9
Classifier: Programming Language :: Python :: 3.10
Classifier: Programming Language :: Python :: 3.11
Classifier: Programming Language :: Python :: 3.12
Classifier: Topic :: Software Development :: Libraries
Provides-Extra: docs
Requires-Dist: Sphinx (>=5.0,<6.0) ; extra == "docs"
Requires-Dist: bluetooth-data-tools (>=0.1.2)
Requires-Dist: bluetooth-sensor-state-data (>=1.5.0)
Requires-Dist: myst-parser (>=0.18,<0.19) ; extra == "docs"
Requires-Dist: sensor-state-data (>=2.1.2)
Requires-Dist: sphinx-rtd-theme (>=1.0,<2.0) ; extra == "docs"
Project-URL: Bug Tracker, https://github.com/bluetooth-devices/qingping-ble/issues
Project-URL: Changelog, https://github.com/bluetooth-devices/qingping-ble/blob/main/CHANGELOG.md
Project-URL: Documentation, https://qingping-ble.readthedocs.io
Project-URL: Repository, https://github.com/bluetooth-devices/qingping-ble
